{
    "commentary": "These are color words functioning as nouns. Linguistic test: 'Red is my favorite color.' or 'The blue was very bright.'",
    "words": {
        "red": null,
        "blue": null,
        "green": null,
        "yellow": null,
        "orange": null,
        "purple": null,
        "pink": null,
        "black": null,
        "white": null,
        "brown": null,
        "gray": null,
        "grey": null,
        "gold": null,
        "silver": null,
        "violet": null,
        "indigo": null,
        "turquoise": null,
        "cyan": null,
        "magenta": null,
        "maroon": null,
        "navy": null,
        "lime": null,
        "olive": null,
        "tan": null,
        "beige": null,
        "crimson": null,
        "scarlet": null,
        "azure": null,
        "emerald": null,
        "ruby": null,
        "sapphire": null,
        "amber": null,
        "coral": null,
        "salmon": null,
        "peach": null,
        "lavender": null,
        "mint": null,
        "cream": null,
        "ivory": null,
        "charcoal": null
    },
    "classes": []
} 